ragkit/__init__.py
ragkit/_base.py
ragkit/agent/__init__.py
ragkit/agent/agent.py
ragkit/chunking/_base.py
ragkit/chunking/markdown.py
ragkit/document/__init__.py
ragkit/document/document.py
ragkit/document/index/__init__.py
ragkit/document/index/_base.py
ragkit/document/index/elastic_search.py
ragkit/document/index/keywords.py
ragkit/document/index/vector_store.py
ragkit/document/retriever/__init__.py
ragkit/document/retriever/_base.py
ragkit/exceptions.py
ragkit/parser/_base.py
ragkit/parser/ingest4llm.py
ragkit/pipeline/__init__.py
ragkit/pipeline/_consts.py
ragkit/pipeline/callback.py
ragkit/pipeline/modules.py
ragkit/pipeline/pipeline.py
ragkit/pipeline/vanilla.py
ragkit/utils/__init__.py
ragkit/utils/postprocessing/__init__.py
ragkit/utils/postprocessing/json.py
ragkit/utils/time.py
ragkit-0.1.0.dist-info/METADATA
ragkit-0.1.0.dist-info/WHEEL
ragkit-0.1.0.dist-info/RECORD
